impresso_commons/__init__.py
impresso_commons/classes/__init__.py
impresso_commons/classes/contentitem.py
impresso_commons/data/config/GDL.json
impresso_commons/data/config/JDG.json
impresso_commons/data/config/cluster.json
impresso_commons/data/config/conf.json
impresso_commons/data/config/conf2.json
impresso_commons/data/config/patch_rebuilt_1.json
impresso_commons/data/config/patch_rebuilt_2.json
impresso_commons/data/config/patch_rebuilt_3.json
impresso_commons/data/config/patch_rebuilt_4.json
impresso_commons/data/config/patch_rebuilt_5.json
impresso_commons/data/config/patch_rebuilt_6.json
impresso_commons/data/config/patch_rebuilt_7.json
impresso_commons/data/config/patch_rebuilt_8.json
impresso_commons/data/config/patch_rebuilt_9.json
impresso_commons/data/config/rebuilt_passim.json
impresso_commons/data/config/rebuilt_passim_1.json
impresso_commons/data/config/rebuilt_passim_2.json
impresso_commons/data/config/rebuilt_passim_3.json
impresso_commons/data/config/remaining_nps.json
impresso_commons/data/xmi/typesystem.xml
impresso_commons/images/__init__.py
impresso_commons/images/img_utils.py
impresso_commons/images/olive_boxes.py
impresso_commons/path/__init__.py
impresso_commons/path/path_fs.py
impresso_commons/path/path_s3.py
impresso_commons/schemas/LICENSE
impresso_commons/schemas/Makefile
impresso_commons/schemas/Pipfile
impresso_commons/schemas/Pipfile.lock
impresso_commons/schemas/README.md
impresso_commons/schemas/requirements.txt
impresso_commons/schemas/json/entities/entities.schema.json
impresso_commons/schemas/json/language_identification/language_identification.schema.json
impresso_commons/schemas/json/linguistic_annotation/ling_spacy.schema.json
impresso_commons/schemas/json/newspaper/contentitem.schema.json
impresso_commons/schemas/json/newspaper/issue.schema.json
impresso_commons/schemas/json/newspaper/page.schema.json
impresso_commons/schemas/json/topic_model/topic_assignment.schema.json
impresso_commons-1.1.2.dist-info/LICENSE
impresso_commons-1.1.2.dist-info/METADATA
impresso_commons-1.1.2.dist-info/WHEEL
impresso_commons-1.1.2.dist-info/entry_points.txt
impresso_commons-1.1.2.dist-info/top_level.txt
impresso_commons-1.1.2.dist-info/RECORD
