Metadata-Version: 2.1
Name: impresso_commons
Version: 1.1.2
Summary: Python module highly reusable within impresso.
Author-email: Maud Ehrmann <maud.ehrmann@epfl.ch>, Matteo Romanello <matteo.romanello@gmail.com>
License: GNU AFFERO GENERAL PUBLIC LICENSE
Project-URL: Homepage, https://github.com/impresso/impresso-pycommons
Project-URL: Documentaton, https://impresso-pycommons.readthedocs.io/en/latest/
Classifier: Programming Language :: Python :: 3
Classifier: Intended Audience :: Developers
Classifier: Intended Audience :: Science/Research
Classifier: License :: OSI Approved :: GNU Affero General Public License v3 or later (AGPLv3+)
Classifier: Operating System :: OS Independent
Classifier: Programming Language :: Python :: 3 :: Only
Classifier: Programming Language :: Python :: 3.7
Classifier: Programming Language :: Python :: 3.10
Classifier: Programming Language :: Python :: 3.11
Requires-Python: >=3.6
License-File: LICENSE
Requires-Dist: aiohttp >=3.8.5
Requires-Dist: aioitertools >=0.11.0
Requires-Dist: aiosignal >=1.3.1
Requires-Dist: alabaster >=0.7.13
Requires-Dist: anyio >=3.7.1
Requires-Dist: appnope >=0.1.3
Requires-Dist: argon2-cffi >=23.1.0
Requires-Dist: argon2-cffi-bindings >=21.2.0
Requires-Dist: arrow >=1.2.3
Requires-Dist: asttokens >=2.4.0
Requires-Dist: async-lru >=2.0.4
Requires-Dist: async-timeout >=4.0.3
Requires-Dist: attrs >=22.2.0
Requires-Dist: Babel >=2.12.1
Requires-Dist: backcall >=0.2.0
Requires-Dist: beautifulsoup4 >=4.12.2
Requires-Dist: bleach >=6.0.0
Requires-Dist: bokeh >=3.2.2
Requires-Dist: boto3 >=1.28.43
Requires-Dist: botocore >=1.31.45
Requires-Dist: build >=1.0.3
Requires-Dist: cachetools >=5.3.1
Requires-Dist: certifi >=2023.7.22
Requires-Dist: cffi >=1.15.1
Requires-Dist: chardet >=5.2.0
Requires-Dist: charset-normalizer >=3.2.0
Requires-Dist: click >=8.1.7
Requires-Dist: cloudpickle >=2.2.1
Requires-Dist: cmake >=3.27.6
Requires-Dist: colorama >=0.4.6
Requires-Dist: colorclass >=2.2.2
Requires-Dist: comm >=0.1.4
Requires-Dist: contourpy >=1.1.0
Requires-Dist: dask >=2023.9.3
Requires-Dist: dask[complete] >=2023.9.3
Requires-Dist: debugpy >=1.7.0
Requires-Dist: decorator >=5.1.1
Requires-Dist: defusedxml >=0.7.1
Requires-Dist: Deprecated >=1.2.14
Requires-Dist: deprecation >=2.1.0
Requires-Dist: distlib >=0.3.7
Requires-Dist: distro >=1.8.0
Requires-Dist: dkpro-cassis
Requires-Dist: docopt >=0.6.2
Requires-Dist: docutils >=0.18.1
Requires-Dist: executing >=1.2.0
Requires-Dist: fastjsonschema >=2.18.0
Requires-Dist: filelock >=3.12.3
Requires-Dist: flake8 >=6.1.0
Requires-Dist: fqdn >=1.5.1
Requires-Dist: frozenlist >=1.4.0
Requires-Dist: fsspec >=2023.6.0
Requires-Dist: GitPython >=3.1.0
Requires-Dist: google-auth >=2.23.3
Requires-Dist: h11 >=0.14.0
Requires-Dist: httpcore >=0.17.3
Requires-Dist: httpx >=0.24.1
Requires-Dist: idna >=3.4
Requires-Dist: imagesize >=1.4.1
Requires-Dist: importlib-metadata >=6.8.0
Requires-Dist: importlib-resources >=5.4.0
Requires-Dist: inflection >=0.5.1
Requires-Dist: iniconfig >=2.0.0
Requires-Dist: ipdb >=0.13.13
Requires-Dist: ipykernel >=6.25.2
Requires-Dist: ipython >=8.15.0
Requires-Dist: ipython-genutils >=0.2.0
Requires-Dist: ipywidgets >=8.1.0
Requires-Dist: iso8601 >=2.1.0
Requires-Dist: isoduration >=20.11.0
Requires-Dist: isort >=5.12.0
Requires-Dist: jedi >=0.19.0
Requires-Dist: Jinja2 >=3.1.2
Requires-Dist: jmespath >=1.0.1
Requires-Dist: json5 >=0.9.14
Requires-Dist: jsonlines >=4.0.0
Requires-Dist: jsonpointer >=2.4
Requires-Dist: jsonschema >=4.19.1
Requires-Dist: jsonschema-specifications >=2023.7.1
Requires-Dist: jupyter >=1.0.0
Requires-Dist: jupyter-console >=6.6.3
Requires-Dist: jupyter-events >=0.7.0
Requires-Dist: jupyter-lsp >=2.2.0
Requires-Dist: jupyter-client >=8.3.1
Requires-Dist: jupyter-core >=5.3.1
Requires-Dist: jupyter-server >=2.7.3
Requires-Dist: jupyter-server-terminals >=0.4.4
Requires-Dist: jupyterlab >=4.0.5
Requires-Dist: jupyterlab-pygments >=0.2.2
Requires-Dist: jupyterlab-widgets >=3.0.8
Requires-Dist: jupyterlab-server >=2.24.0
Requires-Dist: kopf >=1.36.2
Requires-Dist: kr8s >=0.8.16
Requires-Dist: kubernetes >=28.1.0
Requires-Dist: kubernetes-asyncio >=28.2.0
Requires-Dist: locket >=1.0.0
Requires-Dist: lxml >=4.9.3
Requires-Dist: lz4 >=4.3.2
Requires-Dist: Markdown >=3.4.4
Requires-Dist: markdown-it-py >=3.0.0
Requires-Dist: MarkupSafe >=2.1.3
Requires-Dist: matplotlib-inline >=0.1.6
Requires-Dist: mccabe >=0.7.0
Requires-Dist: mdurl >=0.1.2
Requires-Dist: mistune >=3.0.1
Requires-Dist: more-itertools >=8.12.0
Requires-Dist: msgpack >=1.0.5
Requires-Dist: multidict >=6.0.4
Requires-Dist: myst-parser
Requires-Dist: nbclient >=0.8.0
Requires-Dist: nbconvert >=7.8.0
Requires-Dist: nbformat >=5.9.2
Requires-Dist: nest-asyncio >=1.5.7
Requires-Dist: notebook >=7.0.3
Requires-Dist: notebook-shim >=0.2.3
Requires-Dist: numpy >=1.25.2
Requires-Dist: oauthlib >=3.2.2
Requires-Dist: opencv-python >=4.9.0
Requires-Dist: overrides >=7.4.0
Requires-Dist: packaging >=23.1
Requires-Dist: pandas >=2.1.0
Requires-Dist: pandocfilters >=1.5.0
Requires-Dist: parso >=0.8.3
Requires-Dist: partd >=1.4.0
Requires-Dist: pathspec >=0.11.2
Requires-Dist: pexpect >=4.8.0
Requires-Dist: pickleshare >=0.7.5
Requires-Dist: Pillow >=10.0.0
Requires-Dist: pip-upgrader >=1.4.15
Requires-Dist: pipenv >=2023.10.3
Requires-Dist: platformdirs >=3.10.0
Requires-Dist: pluggy >=1.3.0
Requires-Dist: prometheus-client >=0.17.1
Requires-Dist: prompt-toolkit >=3.0.39
Requires-Dist: psutil >=5.9.5
Requires-Dist: ptyprocess >=0.7.0
Requires-Dist: pure-eval >=0.2.2
Requires-Dist: pyarrow >=13.0.0
Requires-Dist: pyasn1 >=0.5.0
Requires-Dist: pyasn1-modules >=0.3.0
Requires-Dist: pycodestyle >=2.11.0
Requires-Dist: pycparser >=2.21
Requires-Dist: pyflakes >=3.1.0
Requires-Dist: Pygments >=2.16.1
Requires-Dist: pykube-ng >=23.6.0
Requires-Dist: pyproject-api >=1.6.1
Requires-Dist: pyproject-hooks >=1.0.0
Requires-Dist: pyrsistent >=0.19.3
Requires-Dist: pytest >=7.4.2
Requires-Dist: python-box >=7.1.1
Requires-Dist: python-dateutil >=2.8.2
Requires-Dist: python-dotenv >=1.0.1
Requires-Dist: python-json-logger >=2.0.7
Requires-Dist: python-jsonpath >=0.7.1
Requires-Dist: python-jsonschema-objects >=0.5.0
Requires-Dist: pytz >=2023.3.post1
Requires-Dist: PyYAML >=6.0.1
Requires-Dist: pyzmq >=25.1.1
Requires-Dist: qtconsole >=5.4.4
Requires-Dist: QtPy >=2.4.0
Requires-Dist: referencing >=0.30.2
Requires-Dist: regex >=2023.8.8
Requires-Dist: requests >=2.31.0
Requires-Dist: requests-oauthlib >=1.3.1
Requires-Dist: rfc3339-validator >=0.1.4
Requires-Dist: rfc3986-validator >=0.1.1
Requires-Dist: rich >=13.6.0
Requires-Dist: rpds-py >=0.10.2
Requires-Dist: rsa >=4.9
Requires-Dist: s3fs >=2023.6.0
Requires-Dist: s3transfer >=0.6.2
Requires-Dist: scikit-build >=0.17.6
Requires-Dist: Send2Trash >=1.8.2
Requires-Dist: six >=1.16.0
Requires-Dist: smart-open >=6.4.0
Requires-Dist: sniffio >=1.3.0
Requires-Dist: snowballstemmer >=2.2.0
Requires-Dist: sortedcontainers >=2.4.0
Requires-Dist: soupsieve >=2.5
Requires-Dist: Sphinx >=7.2.6
Requires-Dist: sphinx-rtd-theme >=1.3.0
Requires-Dist: sphinxcontrib-applehelp >=1.0.7
Requires-Dist: sphinxcontrib-devhelp >=1.0.5
Requires-Dist: sphinxcontrib-htmlhelp >=2.0.4
Requires-Dist: sphinxcontrib-jquery >=4.1
Requires-Dist: sphinxcontrib-jsmath >=1.0.1
Requires-Dist: sphinxcontrib-qthelp >=1.0.6
Requires-Dist: sphinxcontrib-serializinghtml >=1.1.9
Requires-Dist: stack-data >=0.6.2
Requires-Dist: tblib >=2.0.0
Requires-Dist: terminado >=0.17.1
Requires-Dist: terminaltables >=3.1.10
Requires-Dist: tinycss2 >=1.2.1
Requires-Dist: toml >=0.10.2
Requires-Dist: toolz >=0.12.0
Requires-Dist: toposort >=1.7
Requires-Dist: tornado >=6.3.3
Requires-Dist: tox >=4.11.2
Requires-Dist: tqdm
Requires-Dist: traitlets >=5.9.0
Requires-Dist: typing-extensions >=4.8.0
Requires-Dist: tzdata >=2023.3
Requires-Dist: uri-template >=1.3.0
Requires-Dist: urllib3 >=1.26.16
Requires-Dist: virtualenv >=20.24.4
Requires-Dist: wcwidth >=0.2.6
Requires-Dist: webcolors >=1.13
Requires-Dist: webencodings >=0.5.1
Requires-Dist: websocket-client >=1.6.2
Requires-Dist: widgetsnbextension >=4.0.8
Requires-Dist: wrapt >=1.15.0
Requires-Dist: xyzservices >=2023.7.0
Requires-Dist: yarl >=1.9.2
Requires-Dist: zict >=3.0.0
Requires-Dist: zipp >=3.16.2
